giving/__init__.py
giving/api.py
giving/executors.py
giving/extraops.py
giving/gvn.py
giving/gvr.py
giving/operators.py
giving/utils.py
giving/version.py
giving-0.4.3.dist-info/METADATA
giving-0.4.3.dist-info/WHEEL
giving-0.4.3.dist-info/licenses/LICENSE
giving-0.4.3.dist-info/RECORD
