Metadata-Version: 2.3
Name: giving
Version: 0.4.3
Summary: Reactive logging
Project-URL: Homepage, https://giving.readthedocs.io
Project-URL: Repository, https://github.com/breuleux/giving
Project-URL: Documentation, https://giving.readthedocs.io
License-File: LICENSE
Requires-Python: >=3.8
Requires-Dist: asttokens>=2.4.1
Requires-Dist: reactivex>=4.0.4
Requires-Dist: varname>=0.13.3
